pi_monitor/__init__.py
pi_monitor/configuration.py
pi_monitor/enums.py
pi_monitor/healthchecks.py
pi_monitor/notifications.py
pi_monitor/statuspage_io.py
pi_monitor/statuspage_io_client.py
spydersoft_pi_monitor-2.0.0.dist-info/licenses/LICENSE
spydersoft_pi_monitor-2.0.0.dist-info/METADATA
spydersoft_pi_monitor-2.0.0.dist-info/WHEEL
spydersoft_pi_monitor-2.0.0.dist-info/entry_points.txt
spydersoft_pi_monitor-2.0.0.dist-info/top_level.txt
spydersoft_pi_monitor-2.0.0.dist-info/RECORD
