Metadata-Version: 2.4
Name: spydersoft-pi-monitor
Version: 2.0.0
Summary: Simple Python Website Monitoring
Home-page: https://github.com/spydersoft-consulting/md_to_conf
Author: Spydersoft Consulting
Classifier: Programming Language :: Python :: 3 :: Only
License-File: LICENSE
Requires-Dist: pyyaml
Requires-Dist: requests
Requires-Dist: coloredlogs
Requires-Dist: sendgrid
Dynamic: author
Dynamic: classifier
Dynamic: description
Dynamic: description-content-type
Dynamic: home-page
Dynamic: license-file
Dynamic: requires-dist
Dynamic: summary
